odoo8_addon_account_move_line_product-8.0.1.0.0-py2.7-nspkg.pth
odoo8_addon_account_move_line_product-8.0.1.0.0.dist-info/top_level.txt
odoo8_addon_account_move_line_product-8.0.1.0.0.dist-info/WHEEL
odoo8_addon_account_move_line_product-8.0.1.0.0.dist-info/RECORD
odoo8_addon_account_move_line_product-8.0.1.0.0.dist-info/metadata.json
odoo8_addon_account_move_line_product-8.0.1.0.0.dist-info/DESCRIPTION.rst
odoo8_addon_account_move_line_product-8.0.1.0.0.dist-info/METADATA
odoo8_addon_account_move_line_product-8.0.1.0.0.dist-info/namespace_packages.txt
odoo_addons/account_move_line_product/__openerp__.py
odoo_addons/account_move_line_product/__init__.py
odoo_addons/account_move_line_product/README.rst
odoo_addons/account_move_line_product/views/account_move_line_view.xml
odoo_addons/account_move_line_product/static/description/icon.png
