Metadata-Version: 2.0
Name: odoo8-addon-account-move-line-product
Version: 8.0.1.0.0
Summary: Account Move Line Product
Home-page: http://www.eficent.com
Author: Eficent, Odoo Community Association (OCA)
Author-email: support@odoo-community.org
License: AGPL-3
Platform: UNKNOWN
Requires-Dist: odoo (<9.0a,>=8.0a)
Classifier: Programming Language :: Python :: 2.7
Classifier: Framework :: Odoo
Classifier: License :: OSI Approved :: GNU Affero General Public License v3
